pg_channel/__init__.py
pg_channel-0.0.5.dist-info/METADATA
pg_channel-0.0.5.dist-info/WHEEL
pg_channel-0.0.5.dist-info/top_level.txt
pg_channel-0.0.5.dist-info/RECORD
