Metadata-Version: 2.2
Name: pg-channel
Version: 0.0.5
Summary: Generates PL/pgSQL script creating LISTEN/NOTIFY channels
Author-email: Mike Artemiev <mixartemev@gmail.com>
License: MIT
Project-URL: Homepage, https://github.com/XyncNet/pg-channel
Project-URL: Repository, https://github.com/XyncNet/pg-channel
Requires-Python: >=3.11
Provides-Extra: dev
Requires-Dist: pytest; extra == "dev"
Requires-Dist: build; extra == "dev"
Requires-Dist: twine; extra == "dev"
Requires-Dist: setuptools_scm; extra == "dev"
